LICENSE
MANIFEST.in
README.rst
setup.cfg
setup.py
eq_django_admin_row_actions/__init__.py
eq_django_admin_row_actions/admin.py
eq_django_admin_row_actions/components.py
eq_django_admin_row_actions/utils.py
eq_django_admin_row_actions/views.py
eq_django_admin_row_actions.egg-info/PKG-INFO
eq_django_admin_row_actions.egg-info/SOURCES.txt
eq_django_admin_row_actions.egg-info/dependency_links.txt
eq_django_admin_row_actions.egg-info/requires.txt
eq_django_admin_row_actions.egg-info/top_level.txt
eq_django_admin_row_actions/locale/ru_RU/LC_MESSAGES/django.po
eq_django_admin_row_actions/locale/zh_Hant/LC_MESSAGES/django.mo
eq_django_admin_row_actions/locale/zh_Hant/LC_MESSAGES/django.po
eq_django_admin_row_actions/static/css/jquery.dropdown.min.css
eq_django_admin_row_actions/static/js/jquery.dropdown.js
eq_django_admin_row_actions/static/js/jquery.dropdown.min.js
eq_django_admin_row_actions/templates/django_admin_row_actions/dropdown.html
eq_django_admin_row_actions/tests/__init__.py
eq_django_admin_row_actions/tests/tests.py